{"value": [{"img_link": "http://i.ytimg.com/vi/GEGUMIDPVqM/default.jpg", "title": "Bani"}, {"img_link": "http://i.ytimg.com/vi/8JXQhT0KdeY/default.jpg", "title": "Uttaran"}, {"img_link": "http://i.ytimg.com/vi/2ddYLclFwsI/default.jpg", "title": "Rangrasiya"}, {"img_link": "http://i.ytimg.com/vi/7tnHBMe558E/default.jpg", "title": "Sanskaar"}, {"img_link": "http://i.ytimg.com/vi/nEEySo3MnOQ/default.jpg", "title": "Balika Vadhu"}, {"img_link": "http://i.ytimg.com/vi/-bm3_5owBBY/default.jpg", "title": "Sasural Simar Ka"}, {"img_link": "http://i.ytimg.com/vi/RBGZyf4keyY/default.jpg", "title": "Madhubala"}, {"img_link": "http://i.ytimg.com/vi/Y_knSa7GvrQ/default.jpg", "title": "Beintehaa"}, {"img_link": "http://i.ytimg.com/vi/7db8oVg_bLw/default.jpg", "title": "Mission Sapne: Starts 27th April"}, {"img_link": "http://i.ytimg.com/vi/zetAEWHNVRE/default.jpg", "title": "Khatron Ke Khiladi: Darr Ka Blockbuster"}, {"img_link": "http://i.ytimg.com/vi/tM_wdgwmDAE/default.jpg", "title": "Sasural Simar Ka: 22nd April"}, {"img_link": "http://i.ytimg.com/vi/n1ZrEs3G2R4/default.jpg", "title": "Madhubala: Mo"}, {"img_link": "http://i.ytimg.com/vi/cH6ps4tdt2U/default.jpg", "title": "Mission Sapne: Salman Kha"}, {"img_link": "http://i.ytimg.com/vi/5ymoamiuyDo/default.jpg", "title": "Mission Sapne: Ranbir Kapoo"}]}